kwantspectrum/__init__.py
kwantspectrum/_kwant_spectrum_version.py
kwantspectrum/kwant_spectrum.py
kwantspectrum/version.py
kwantspectrum/tests/__init__.py
kwantspectrum/tests/test_kwant_spectrum.py
kwantspectrum-0.1.1.dist-info/LICENSE.rst
kwantspectrum-0.1.1.dist-info/METADATA
kwantspectrum-0.1.1.dist-info/WHEEL
kwantspectrum-0.1.1.dist-info/top_level.txt
kwantspectrum-0.1.1.dist-info/RECORD
