Metadata-Version: 2.1
Name: kwantspectrum
Version: 0.1.1
Summary: Adaptive band structure analyzer for Kwant leads
Home-page: https://gitlab.kwant-project.org/kwant/kwantspectrum
Author: T. Kloss, C. W. Groth, X. Waintal, et al.
Author-email: kloss@itp.uni-frankfurt.de
License: UNKNOWN
Keywords: physics kwant bandstructure
Platform: UNKNOWN
Classifier: Development Status :: 4 - Beta
Classifier: Intended Audience :: Science/Research
Classifier: Intended Audience :: Developers
Classifier: Topic :: Software Development
Classifier: Topic :: Scientific/Engineering
Classifier: License :: OSI Approved :: BSD License
Classifier: Programming Language :: Python :: 3 :: Only
Requires-Python: >=3.5
Requires-Dist: kwant (>=1.4)
Requires-Dist: numpy
Requires-Dist: scipy
Provides-Extra: test
Requires-Dist: pytest ; extra == 'test'
Requires-Dist: pytest-cov ; extra == 'test'
Requires-Dist: pytest-flake8 ; extra == 'test'
